{
  "uid": {
    "__TYPE__": "UIDContent",
    "value": "rays"
  },
  "slices": {
    "__TYPE__": "SliceContentType",
    "value": [
      {
        "key": "nav$e6be9f68-d274-43d9-821c-e755f05cabf0",
        "name": "nav",
        "widget": {
          "__TYPE__": "SharedSliceContent",
          "variation": "default",
          "primary": {
            "title": {
              "__TYPE__": "StructuredTextContent",
              "value": [
                {
                  "type": "heading1",
                  "content": {
                    "text": "Tried"
                  }
                }
              ]
            },
            "description": {
              "__TYPE__": "StructuredTextContent",
              "value": [
                {
                  "type": "paragraph",
                  "content": {
                    "text": "Mollit nostrud aliquip amet do elit magna in cupidatat culpa labore aliqua anim. Mollit incididunt fugiat proident in nostrud in incididunt nostrud enim nisi magna enim officia exercitation. In ipsum anim ipsum est pariatur minim."
                  }
                }
              ]
            }
          },
          "items": [
            {
              "__TYPE__": "GroupItemContent",
              "value": [
                [
                  "link",
                  {
                    "__TYPE__": "LinkContent",
                    "value": {
                      "__TYPE__": "ExternalLink",
                      "url": "http://google.com"
                    }
                  }
                ],
                [
                  "label",
                  {
                    "__TYPE__": "FieldContent",
                    "value": "equally",
                    "type": "Text"
                  }
                ]
              ]
            }
          ]
        }
      },
      {
        "key": "hero$2bc00d01-52aa-425c-911a-94cc32543462",
        "name": "hero",
        "widget": {
          "__TYPE__": "SharedSliceContent",
          "variation": "default",
          "primary": {
            "title": {
              "__TYPE__": "StructuredTextContent",
              "value": [
                {
                  "type": "heading1",
                  "content": {
                    "text": "Aboard"
                  }
                }
              ]
            },
            "description": {
              "__TYPE__": "StructuredTextContent",
              "value": [
                {
                  "type": "paragraph",
                  "content": {
                    "text": "Duis cupidatat laboris reprehenderit cupidatat aute aliqua dolore sunt magna quis veniam id."
                  }
                }
              ]
            }
          },
          "items": [
            {
              "__TYPE__": "GroupItemContent",
              "value": [
                [
                  "profile_img",
                  {
                    "__TYPE__": "ImageContent",
                    "origin": {
                      "id": "main",
                      "url": "https://images.unsplash.com/photo-1579931794097-0ad001e51edb",
                      "width": 3958,
                      "height": 3958
                    },
                    "url": "https://images.unsplash.com/photo-1579931794097-0ad001e51edb",
                    "width": 3958,
                    "height": 3958,
                    "edit": {
                      "zoom": 1,
                      "crop": {
                        "x": 0,
                        "y": 0
                      },
                      "background": "transparent"
                    },
                    "thumbnails": {}
                  }
                ]
              ]
            }
          ]
        }
      },
      {
        "key": "footer$4eb51cea-596a-470b-97f7-ae1553765c23",
        "name": "footer",
        "widget": {
          "__TYPE__": "SharedSliceContent",
          "variation": "default",
          "primary": {
            "title": {
              "__TYPE__": "StructuredTextContent",
              "value": [
                {
                  "type": "heading1",
                  "content": {
                    "text": "Excitement"
                  }
                }
              ]
            },
            "description": {
              "__TYPE__": "StructuredTextContent",
              "value": [
                {
                  "type": "paragraph",
                  "content": {
                    "text": "Ut excepteur cillum laborum cillum aliqua voluptate dolore ipsum aliquip consequat proident minim. Nulla amet occaecat cupidatat pariatur mollit sunt aute ad labore nisi pariatur eu voluptate qui. Laboris eu labore voluptate aliquip incididunt enim nisi."
                  }
                }
              ]
            }
          },
          "items": [
            {
              "__TYPE__": "GroupItemContent",
              "value": []
            }
          ]
        }
      }
    ]
  }
}